indexed_meta/__init__.py
indexed_meta-0.0.5.dist-info/LICENSE
indexed_meta-0.0.5.dist-info/METADATA
indexed_meta-0.0.5.dist-info/WHEEL
indexed_meta-0.0.5.dist-info/RECORD
